{
"Common" : {
	"5"	  : "Portamento/Glide",
	"7"   : "Output Level",
	"64"  : "Damper",

    "73"  : "Envelope Attack",
    "75"  : "Envelope Decay",
    "80"  : "Envelope Sustain",
    "72"  : "Envelope Release",
    
	"76"  : "Filter/EG Attack",
    "77"  : "Filter/EG Decay",
    "78"  : "Filter/EG Sustain",
    "79"  : "Filter/EG Release",

	"14"  : "FX I Type",
	"12"  : "FX I Edit 1",
	"13"  : "FX I Edit 2",

	"15"  : "FX II Type",
	"16"  : "FX II Edit 1",
	"17"  : "FX II Edit 2",

	"20"  : "LFO I Shape",
	"21"  : "LFO I Frequency",
	"22"  : { "LFO I Key Sync" : [ "OFF", "ON" ] },    
	"23"  : { "LFO I BPM Sync" : [ "OFF", "ON" ] },    
	
	"24"  : "LFO II Shape",
	"25"  : "LFO II Frequency",
	"26"  : { "LFO II Key Sync" : [ "OFF", "ON" ] },    
	"27"  : { "LFO II BPM Sync" : [ "OFF", "ON" ] }    
},
"Alexandria" : {
	"1"   :	"Modulation Wheel",
	"12"  :	"Mod Fx Edit 1",
	"13"  :	"Mod Fx Edit 2",
	"16"  :	"Ambi Fx Edit 1",
	"17"  :	"Ambi Fx Edit 2",
	"100" :	{ "Rotation" : [ "SLOW", "STOP", "FAST" ] },
	"101" :	{ "Vibrato" : [ "OFF", "ON" ] },
	"103" :	"Drive",
	"102" :	{ "Vibrato Preset" : [ "V-1", "C-1", "V-2", "C-2", "V-3", "C-3" ] }
},
"Kingston" : {
	"81" : { "Waveform" : [ "Triangle", "Pulse 50%", "Pulse 25%", "Pulse 12.5%", "Noise" ] },
	"82" : { "Transpose" : [ "-2", "-1", "0", "1", "2" ] },
	"83" : { "Jump" : [ "OFF", "ON" ] },
	"84" : "Jump Height",
	"85" : { "Run" : [ "OFF", "ON" ] },
	"86" : { "Run Type" : [ "1", "2", "3", "4", "5", "6", "7" ] },
	"87" : "Run Speed",
	"73" : "Env Attack",
	"75" : "Env Decay",
	"72" : "Env Release",
	"80" : "Env Sustain",
	"14" : { "FX Type" : [ "OFF", "EQ", "Comp", "LoFi", "Ring", "Ch/Fl", "Ensemble", "Pump", "Short Delay", "BPM Delay", "Hall Reverb", "Gate Reverb" ] },
	"12" : "FX Edit 1",
	"13" : "FX Edit 2"
},
"Brussels" : {
	"81" : "Performer Repeat",
	"82" : "Performer Pump",
	"83" : "Generator Bottom",
	"5"  : "Generator Glide",
	"84" : "Generator Diffuse",
	"1"  : "Generator Filter",
	"85" : "Generator Twist",
	"13" : "Reverb Tone",
	"12" : "Reverb Level"
},
"Miami" : {
	"81" : { "Carrier Wave" : [ "Triangle", "Saw", "Square" ] },
	"82" : "Carrier Level",
	"83" : "Carrier Sub",
	"84" : "Carrier Pitch",
	"5" : "Output Glide",
	"85" : "XMod Level",
	"86" : { "XMod Wave" : [ "Triangle", "Saw", "Square", "Pulse" ] },
	"87" : "XMod Tune",
	"88" : "XMod Depth",
	"1" : "Filter Cutoff",
	"71" : "Filter Crush",
	"89" : { "Wobble Shape" : [ "Triangle", "DownSaw", "UpSaw", "Square" ] },
	"90" : "Wobble Depth", 
	"91" : { "Wobble Rate" : [ "1/2", "1/4", "1/8", "1/16", "1/3", "1/6", "1/12", "1/24" ] },
	"92" : "Output Stereo"
},
"ChiangMai" : {
	"73" : "Amp Attack",
	"75" : "Amp Decay",
	"72" : "Amp Release",
	"80" : "Amp Sustain",
	"15" : "Chorus Depth",
	"16" : "Chorus Speed",
	"12" : "Delay Level",
	"13" : "Delay Time",
	"76" : "Filter Attack",
	"77" : "Filter Decay",
	"30" : "Filter EG Amt",
	"1"  : "Filter Freq",
	"31" : "Filter Kbd Amt",
	"79" : "Filter Release",
	"71" : "Filter Reso",
	"78" : "Filter Sustain",
	"85" : "OSC1 Depth",
	"86" : "OSC1 EG Amt",
	"84" : "OSC1 Harmonics [13]",
	"81" : "OSC1 Level",
	"83" : "OSC1 Pitch",
	"82" : { "OSC1 Waveform" : [ "Pulse", "Saw", "Sine", "Square", "Tri" ] },
	"91" : "OSC2 Depth",
	"92" : "OSC2 EG Amt",
	"90" : "OSC2 Harmonics [13]",
	"87" : "OSC2 Level",
	"89" : "OSC2 Pitch",
	"88" : { "OSC2 Waveform" : [ "Pulse", "Saw", "Sine", "Square", "Tri" ] }
},
"Berlin" : {
	"13" : "Delay Level",
	"14" : { "Delay Spread" : [ "OFF", "ON" ] },
	"12" : "Delay Time",
	"76" : "EG1 Attack",
	"77" : "EG1 Decay",
	"23" : { "LFO BPM Sync" : [ "OFF", "ON" ] },
	"21" : "LFO Freq",
	"22" : { "LFO Key Sync" : [ "OFF", "ON" ] },
	"20" : { "LFO Shape" : [ "Triangle", "DownSaw", "UpSaw", "Square", "SH" ] },
	"5" : "Portamento",
	"73" : "VCA Attack",
	"75" : "VCA Decay",
	"72" : "VCA Release",
	"80" : "VCA Sustain",
	"30" : "VCF EG1 Amt",
	"74" : "VCF Freq",
	"31" : "VCF Kbd Amt",
	"29" : "VCF LFO Amt",
	"71" : "VCF Reso",
	"84" : "VCO Balance",
	"87" : { "VCO Legato" : [ "OFF", "ON" ] },
	"85" : "VCO Mod Amt",
	"86" : { "VCO Mod Src" : [ "LFO", "EG1" ] },
	"81" : "VCO Pitch",
	"83" : "VCO Tone",
	"82" : { "VCO Waveform" : [ "Triangle", "Saw", "Square", "Pulse" ] },
	"1" : "Vibrato"
},
"Dublin" : {
	"87" : { "Legato" : [ "OFF", "ON" ] },
	"23" : { "MG1 BPM Sync" : [ "OFF", "ON" ] },
	"21" : "MG1 Frequency",
	"22" : { "MG1 Key Sync" : [ "OFF", "ON" ] },
	"102": "MG1 Mod Amt",
	"20" : { "MG1 Waveform" : [ "Triangle", "Saw", "Square", "SH" ] },
	"27" : { "MG2 BPM Sync" : [ "OFF", "ON" ] },
	"25" : "MG2 Frequency",
	"26" : { "MG2 Key Sync" : [ "OFF", "ON" ] },
	"103": "MG2 Mod Amt",
	"24" : { "MG2 Waveform" : [ "Triangle", "Saw", "Square", "SH" ] },
	"76" : "MOD EG A",
	"104": "MOD EG Amt",
	"77" : "MOD EG D",
	"79" : "MOD EG R",
	"78" : "MOD EG S",
	"12" : "Master Drive",
	"13" : "Master Tone",
	"90" : "Mixer Noise Level",
	"88" : "Mixer VCO1 Level",
	"89" : "Mixer VCO2 Level",
	"5"  : "Portamento",
	"73" : "VCA Attack",
	"75" : "VCA Decay",
	"72" : "VCA Release",
	"80" : "VCA Sustain",
	"1"  : "VCF Cutoff",
	"31" : "VCF Kbd Amt",
	"71" : "VCF Peak",
	"83" : { "VCO1 Scale" : [ "32", "16", "8", "4" ] },
	"82" : "VCO1 Shape",
	"81" : { "VCO1 Waveform" : [ "Tri", "Saw", "Square/Pulse" ] },
	"86" : { "VCO2 Scale" : [ "32", "16", "8", "4" ] },
	"85" : "VCO2 Tune",
	"84" : { "VCO2 Waveform" : [ "Tri", "Saw", "Square/Pulse" ] }
},
"Helsinki" : {
	"73" : "Env Attack",
	"75" : "Env Decay",
	"72" : "Env Release",
	"80" : "Env Sustain",
	"29" : { "Filter Type" : [ "LPF12", "LPF24", "BPF", "HPF" ] },
	"1"  : "Filter Freq",
	"71" : "Filter Reso",
	"83" : "Generator High",
	"84" : "Generator Higher",
	"82" : "Generator Low",
	"85" : "Generator Noise",
	"81" : { "Generator Type" : [ "Triangle", "Saw", "Square" ] },
	"12" : "LoFi Freq",
	"13" : "LoFi Mix",
	"15" : "Reverb Level",
	"16" : "Reverb Time"
},
"Phoenix" : {
	"1" : "Vibrato Depth",
	"5" : "Portamento",
	"12" : "Delay Level",
	"13" : "Delay Time",
	"14" : "Delay Tone",
	"20" : { "LFO Waveform" : [ "Sine", "Saw", "Rect", "SH" ] },
	"21" : "LFO Rate",
	"22" : { "LFO Key Sync" : [ "OFF", "ON" ] },
	"23" : { "LFO BPM Sync" : [ "OFF", "ON" ] },
	"24" : "Vibrato Rate",
	"30" : "Filter Env Amt",
	"31" : "Filter Kbd Amt",
	"71" : "Filter Reso",
	"72" : "Amp Release",
	"73" : "Amp Attack",
	"74" : "Filter Freq",
	"75" : "Amp Decay",
	"76" : "Filter Attack",
	"77" : "Filter Decay",
	"78" : "Filter Sustain",
	"79" : "Filter Release",
	"80" : "Amp Sustain",
	"81" : { "OSC1 Waveform" : [ "Triangle", "Saw", "Pulse" ] },
	"82" : "OSC1 Pitch",
	"83" : "OSC Balance",
	"84" : "Pulse Width",
	"85" : { "OSC2 Waveform" : [ "Triangle", "Saw", "Pulse" ] },
	"86" : "OSC2 Pitch",
	"87" : "OSC2 Detune",
	"88" : "P.Bend Range",
	"102": "Mod Depth Pulse Width",
	"103": "Mod Depth Filter",
	"104": "Mod Depth Amp",
	"105": { "Unison" : [ "OFF", "ON" ] },
	"106": "Unison Detune"
},
"Chicago" : {
	"81"  : "OSC Waveform",
	"5"	  : "Glide",
	"1"   : "VCF Cutoff",
    "71"  : "VCF Peak",
    "30"  : "VCF Env Amt",
    "82"  : "VCF Bite",
    "83"  : "VCF Gnaw",
    "73"  : "Env Attack",
    "75"  : "Env Decay",
    "80"  : "Env Sustain",
    "72"  : "Env Release",
    "84"  : { "Amp Mode" : [ "Env", "Gate" ] },
    "85"  : { "Arp Switch" : [ "OFF", "ON" ] },
    "86"  : { "Arp Mode" : [ "Down", "Up", "Up/Dn" ] } ,
    "87"  : { "Arp Range" : [ "1 Oct", "2 Oct", "Full" ] },
    "88"  : "Arp Speed",
    "14"  : { "FX Type" : [ "EQ", "Comp", "Decimator", "RingMod", "Cho/Flg", "Ensemble", "Phaser", "Short Delay", "BPM Delay", "Hall Reverb", "Gate Reverb" ] },
    "12"  : "FX Edit 1",
    "13"  : "FX Edit 2"
},
"Firenze" : {
	"1"	  : "Modulation Wheel",
	"12"  : "Mod Fx Edit 1",
	"13"  : "Mod Fx Edit 2",
	"16"  : "Ambi Fx Edit 1",
    "17"  : "Ambi Fx Edit 2",
    "100" : { "Presence" : [ "OFF", "ON" ] },
    "101" : { "Treble" : [ "OFF", "ON" ] },
    "102" : { "Medium" : [ "OFF", "ON" ] },
    "103" : { "Bass" : [ "OFF", "ON" ] },
    "71"  : "Keyoff Noise",
    "104" : "Mute"
},
"Montreal" : {
	"1"	  : "Modulation Wheel",
	"12"  : "Mod Fx Edit 1",
	"13"  : "Mod Fx Edit 2",
	"16"  : "Ambi Fx Edit 1",
    "17"  : "Ambi Fx Edit 2",
    "71"  : { "Keyoff Noise" : [ "OFF", "ON" ] },
    "72"  : "Release Time",
    "100" : "EQ High",
	"101" : "EQ Low",
	"102" : { "Tremolo" : [ "OFF", "Mono", "Stereo" ] },
	"103" : "Tremolo Depth",
	"104" : "Tremolo Speed",
	"105" : { "Amp" : [ "OFF", "ON" ] },
	"106" : "Amp Drive" 	
},
"Wolfsburg" : {
	"81"  : { "OSC1 Waveform" : [ "Triangle", "Saw", "Pulse 50%", "Pulse 25%", "Pulse 12.5%" ] },
	"82"  : "OSC1 Pitch",
	"83"  : "OSC1 Level",
	"84"  : "OSC1 Detune",
	"85"  : { "OSC2 Waveform" : [ "Triangle", "Saw", "Pulse 50%", "Pulse 25%", "Pulse 12.5%" ] },
	"86"  : "OSC2 Pitch",
	"87"  : "OSC2 Level",
	"88"  : "OSC2 Detune",
	"89"  : "Noise Level",
	"5"   : "Portamento",
 	"29"  : "Filter Type",
	"1"   : "Filter Cutoff",
	"71"  : "Filter Resonance",
	"30"  : "Filter Env Amt",
	"73"  : "Amp Env A",
	"75"  : "Amv Env D",
	"80"  : "Amv Env S",
	"72"  : "Amv Emv R",
	"76"  : "Mod Env A",
	"77"  : "Mod Env D",
	"78"  : "Mod Env S",
	"79"  : "Mod Env R",
	"20"  : { "LFO1 Waveform" : [ "Triangle", "Saw", "Square", "SH" ] },
	"21"  : "LFO1 Speed",
	"22"  : { "LFO1 Key Sync" : [ "OFF", "ON" ] },
	"23"  : { "LFO1 BPM Sync" : [ "OFF", "ON" ] },
	"24"  : { "LFO2 Waveform" : [ "Triangle", "Saw", "Square", "SH" ] },
	"25"  : "LFO2 Speed",
	"26"  : { "LFO2 Key Sync" : [ "OFF", "ON" ] },
	"27"  : { "LFO2 BPM Sync" : [ "OFF", "ON" ] },
	"90"  : "Matrix A Source [8]",
	"91"  : "Matrix A Dest [18]",
	"102" : "Matrix A Amt",
	"92"  : "Matrix B Source [8]",
	"93"  : "Matrix B Dest [18]",
	"103" : "Matrix B Amt",
	"104" : "Matrix C Amt",
	"105" : "Matrix D Amt",
	"14"  : "FX1 Type",
	"12"  : "FX1 Edit 1",
	"13"  : "FX1 Edit 2",
	"15"  : "FX2 Type",
	"16"  : "FX2 Edit 1",
	"17"  : "FX2 Edit 2"
}
}
